decorator_framework-1.0.4.dist-info/licenses/LICENSE
decorators/__init__.py
decorators/on.py
nucleus/Myclass.py
nucleus/__init__.py
nucleus/dispatcher.py
tests/__init__.py
decorator_framework-1.0.4.dist-info/METADATA
decorator_framework-1.0.4.dist-info/WHEEL
decorator_framework-1.0.4.dist-info/top_level.txt
decorator_framework-1.0.4.dist-info/RECORD
